kcsd/KCSD.py
kcsd/__init__.py
kcsd/basis_functions.py
kcsd/sKCSD.py
kcsd/sKCSD_utils.py
kcsd/utility_functions.py
kcsd/data/ElcoordsDomi14.txt
kcsd/data/sinsyn.mod
kcsd/data/Simple_with_branches/LFP/myLFP
kcsd/data/Simple_with_branches/electrode_positions/elcoord_x_y_z
kcsd/data/Simple_with_branches/morphology/Badea2011Fig2Du.CNG.swc
kcsd/data/Y_shaped_neuron/LFP/MyLFP
kcsd/data/Y_shaped_neuron/electrode_positions/elcoord_x_y_x
kcsd/data/Y_shaped_neuron/morphology/Y_shaped.swc
kcsd/data/ball_and_stick_128/LFP/myLFP
kcsd/data/ball_and_stick_128/electrode_positions/elcoord_x_y_z
kcsd/data/ball_and_stick_128/morphology/ball_and_stick.swc
kcsd/data/ball_and_stick_16/LFP/myLFP
kcsd/data/ball_and_stick_16/electrode_positions/elcoord_x_y_z
kcsd/data/ball_and_stick_16/morphology/ball_and_stick.swc
kcsd/data/ball_and_stick_8/LFP/MyLFP
kcsd/data/ball_and_stick_8/electrode_positions/elcoord_x_y_x
kcsd/data/ball_and_stick_8/morphology/Figure_2_rows_8.swc
kcsd/data/gang_7x7_200/membcurr
kcsd/data/gang_7x7_200/seglength
kcsd/data/gang_7x7_200/somav.txt
kcsd/data/gang_7x7_200/tvec.txt
kcsd/data/gang_7x7_200/LFP/MyLFP
kcsd/data/gang_7x7_200/electrode_positions/elcoord_x_y_z
kcsd/data/gang_7x7_200/morphology/gang_7x7_200_rows_4_cols_5_xmin_-20_xmax_20_ymin_-20_ymax_20_orientation_3.swc
kcsd/data/morphology/Badea2011Fig2Du.CNG.swc
kcsd/data/morphology/DomiCell.swc
kcsd/data/morphology/ElcoordsDomi14.txt
kcsd/data/morphology/L5_Mainen96_LFPy.hoc
kcsd/data/morphology/Mainen_swcLike.swc
kcsd/data/morphology/Test.swc
kcsd/data/morphology/active.hoc
kcsd/data/morphology/ballstick.hoc
kcsd/data/morphology/ballstick.swc
kcsd/data/morphology/morpho1.swc
kcsd/data/morphology/retina_ganglion.swc
kcsd/data/morphology/villa.hoc
kcsd/data/morphology/villa.swc
kcsd/tests/__init__.py
kcsd/tests/api_tests.py
kcsd/tests/kcsd_tests.py
kcsd/tests/test_loadData.py
kcsd/tests/test_sKCSD.py
kcsd/tests/test_sKCSDcell.py
kcsd/tests/test_sKCSDutils.py
kcsd/validation/ValidateKCSD.py
kcsd-2.0.1.dist-info/LICENSE.txt
kcsd-2.0.1.dist-info/METADATA
kcsd-2.0.1.dist-info/WHEEL
kcsd-2.0.1.dist-info/top_level.txt
kcsd-2.0.1.dist-info/RECORD
