Metadata-Version: 2.1
Name: kcsd
Version: 2.0.1
Summary: kernel current source density methods
Home-page: https://github.com/Neuroinflab/kCSD-python
Author: Chaitanya Chintaluri et al
License: Modified BSD License
Keywords: Electrophysiology CSD LFP MEA
Classifier: Development Status :: 5 - Production/Stable
Classifier: License :: OSI Approved :: BSD License
Classifier: Natural Language :: English
Classifier: Programming Language :: Python :: 3
Classifier: Programming Language :: Python :: 3.8
Classifier: Programming Language :: Python :: 3.9
Classifier: Programming Language :: Python :: 3.10
Classifier: Programming Language :: Python :: 3.11
Classifier: Operating System :: OS Independent
Classifier: Topic :: Scientific/Engineering :: Medical Science Apps.
Classifier: Intended Audience :: Science/Research
License-File: LICENSE.txt
Requires-Dist: numpy >=1.19
Requires-Dist: scipy >=1.8.0
Requires-Dist: matplotlib >=3.6
Provides-Extra: docs
Requires-Dist: numpydoc >=1.6.0 ; extra == 'docs'
Requires-Dist: sphinx >=5 ; extra == 'docs'
